Metadata-Version: 2.1
Name: devcon-win
Version: 0.2.4.2
Summary: devcon_win - interact with devcon.exe in NT systems
Home-page: https://github.com/Shivanshu26shiv/devcon_win
Author: Shivanshu Srivastava
Author-email: shivanshu26shiv@gmail.com
License: MIT
Download-URL: https://github.com/Shivanshu26shiv/devcon_win/archive/v_02.4.2.tar.gz
Keywords: devcon,hardware drivers,device drivers,drivers
Platform: UNKNOWN
Classifier: Development Status :: 3 - Alpha
Classifier: Intended Audience :: Developers
Classifier: Topic :: Software Development :: Build Tools
Classifier: Operating System :: Microsoft :: Windows
Classifier: License :: OSI Approved :: MIT License
Classifier: Programming Language :: Python :: 2.7
Classifier: Programming Language :: Python :: 3
Classifier: Programming Language :: Python :: 3
Classifier: Programming Language :: Python :: 3.4
Classifier: Programming Language :: Python :: 3.5
Classifier: Programming Language :: Python :: 3.6
